logger_json/__init__.py
logger_json/formatter.py
logger_json/tests/__init__.py
logger_json/tests/tests.py
logger_json-1.0.3.dist-info/LICENSE.txt
logger_json-1.0.3.dist-info/METADATA
logger_json-1.0.3.dist-info/WHEEL
logger_json-1.0.3.dist-info/top_level.txt
logger_json-1.0.3.dist-info/RECORD
