Metadata-Version: 2.1
Name: logger-json
Version: 1.0.3
Summary: Tool to display logs in JSON format
Home-page: UNKNOWN
Author: Gizem Kacmaz
Author-email: gizemkmz@gmail.com
License: MIT
Keywords: Json,Logger
Platform: UNKNOWN
